{
  "ID": "149849cfbf324cc2a3d42fc4e5c19f91",
  "Name": "DOOM (1993)",
  "Names": [],
  "Rating": 4.91,
  "NumberOfRatings": 35,
  "DailyRatings": 4.87,
  "FirstSeen": "2022-08-19T14:31:30.8251329+00:00",
  "FirstSeenRating": "2022-08-26T00:30:55.8306783+00:00",
  "LastChanged": "2022-08-27T11:00:53.9107243+00:00",
  "RatingHistory": [
    {
      "Time": "2022-08-26T00:30:55.830679+00:00",
      "Rating": 4.89,
      "NumberOfRatings": 28
    },
    {
      "Time": "2022-08-27T00:31:05.8297405+00:00",
      "Rating": 4.91,
      "NumberOfRatings": 33
    },
    {
      "Time": "2022-08-27T11:00:53.9107245+00:00",
      "Rating": 4.91,
      "NumberOfRatings": 35
    }
  ],
  "Tags": []
}