{
  "ID": "8ae3c382222c462492f25bab4800b77d",
  "Name": "Travellers Rest",
  "Names": [],
  "Rating": 4.42,
  "NumberOfRatings": 26,
  "DailyRatings": 0.98,
  "FirstSeen": "2022-08-25T19:31:26.5685992+00:00",
  "FirstSeenRating": "2022-09-04T00:31:40.8839276+00:00",
  "LastChanged": "2022-09-06T01:31:36.8219642+00:00",
  "RatingHistory": [
    {
      "Time": "2022-09-04T00:31:40.8839277+00:00",
      "Rating": 4.38,
      "NumberOfRatings": 24
    },
    {
      "Time": "2022-09-06T01:31:36.8219645+00:00",
      "Rating": 4.42,
      "NumberOfRatings": 26
    }
  ],
  "Tags": []
}