{
  "ID": "7015c51a49be4592b5ba3ae2577723c5",
  "Name": "Tropico 5",
  "Names": [],
  "Rating": 4.44,
  "NumberOfRatings": 1084,
  "DailyRatings": 20.61,
  "FirstSeen": "2022-07-22T20:18:35.4138302+00:00",
  "LastChanged": "2022-07-31T14:30:30.7318704+00:00",
  "RatingHistory": [
    {
      "Time": "2022-07-22T20:18:35.4138307+00:00",
      "Rating": 4.45,
      "NumberOfRatings": 900
    },
    {
      "Time": "2022-07-23T06:00:48.982885+00:00",
      "Rating": 4.45,
      "NumberOfRatings": 912
    },
    {
      "Time": "2022-07-23T10:00:39.5107421+00:00",
      "Rating": 4.45,
      "NumberOfRatings": 913
    },
    {
      "Time": "2022-07-23T11:06:20.0989153+00:00",
      "Rating": 4.45,
      "NumberOfRatings": 915
    },
    {
      "Time": "2022-07-23T13:04:55.3323172+00:00",
      "Rating": 4.45,
      "NumberOfRatings": 916
    },
    {
      "Time": "2022-07-23T14:01:00.0872864+00:00",
      "Rating": 4.45,
      "NumberOfRatings": 917
    },
    {
      "Time": "2022-07-23T16:00:23.2388963+00:00",
      "Rating": 4.45,
      "NumberOfRatings": 923
    },
    {
      "Time": "2022-07-23T20:00:27.2028771+00:00",
      "Rating": 4.45,
      "NumberOfRatings": 924
    },
    {
      "Time": "2022-07-24T08:00:28.6205528+00:00",
      "Rating": 4.45,
      "NumberOfRatings": 930
    },
    {
      "Time": "2022-07-24T14:00:59.6620675+00:00",
      "Rating": 4.45,
      "NumberOfRatings": 937
    },
    {
      "Time": "2022-07-24T16:01:19.8828537+00:00",
      "Rating": 4.45,
      "NumberOfRatings": 941
    },
    {
      "Time": "2022-07-24T20:00:31.62895+00:00",
      "Rating": 4.45,
      "NumberOfRatings": 946
    },
    {
      "Time": "2022-07-25T10:00:54.3776957+00:00",
      "Rating": 4.44,
      "NumberOfRatings": 956
    },
    {
      "Time": "2022-07-25T12:01:21.7628083+00:00",
      "Rating": 4.44,
      "NumberOfRatings": 958
    },
    {
      "Time": "2022-07-25T14:01:36.4262801+00:00",
      "Rating": 4.44,
      "NumberOfRatings": 960
    },
    {
      "Time": "2022-07-25T18:00:49.8109117+00:00",
      "Rating": 4.44,
      "NumberOfRatings": 963
    },
    {
      "Time": "2022-07-25T22:00:30.635131+00:00",
      "Rating": 4.44,
      "NumberOfRatings": 967
    },
    {
      "Time": "2022-07-26T00:00:55.2838349+00:00",
      "Rating": 4.44,
      "NumberOfRatings": 969
    },
    {
      "Time": "2022-07-26T10:00:51.9143431+00:00",
      "Rating": 4.44,
      "NumberOfRatings": 974
    },
    {
      "Time": "2022-07-26T16:00:51.5285696+00:00",
      "Rating": 4.45,
      "NumberOfRatings": 978
    },
    {
      "Time": "2022-07-26T18:00:57.3180191+00:00",
      "Rating": 4.44,
      "NumberOfRatings": 982
    },
    {
      "Time": "2022-07-26T22:00:33.031218+00:00",
      "Rating": 4.44,
      "NumberOfRatings": 987
    },
    {
      "Time": "2022-07-27T02:01:17.8433928+00:00",
      "Rating": 4.44,
      "NumberOfRatings": 991
    },
    {
      "Time": "2022-07-27T08:00:30.5710261+00:00",
      "Rating": 4.44,
      "NumberOfRatings": 992
    },
    {
      "Time": "2022-07-27T12:00:52.6061516+00:00",
      "Rating": 4.44,
      "NumberOfRatings": 994
    },
    {
      "Time": "2022-07-27T16:00:51.4742408+00:00",
      "Rating": 4.44,
      "NumberOfRatings": 996
    },
    {
      "Time": "2022-07-27T18:00:49.3243744+00:00",
      "Rating": 4.44,
      "NumberOfRatings": 1001
    },
    {
      "Time": "2022-07-27T20:00:28.7522529+00:00",
      "Rating": 4.44,
      "NumberOfRatings": 1002
    },
    {
      "Time": "2022-07-28T10:00:29.3666335+00:00",
      "Rating": 4.44,
      "NumberOfRatings": 1010
    },
    {
      "Time": "2022-07-28T14:01:01.4995686+00:00",
      "Rating": 4.44,
      "NumberOfRatings": 1013
    },
    {
      "Time": "2022-07-28T16:00:49.8830918+00:00",
      "Rating": 4.44,
      "NumberOfRatings": 1015
    },
    {
      "Time": "2022-07-28T18:16:41.6608256+00:00",
      "Rating": 4.44,
      "NumberOfRatings": 1020
    },
    {
      "Time": "2022-07-28T23:30:52.9281688+00:00",
      "Rating": 4.44,
      "NumberOfRatings": 1025
    },
    {
      "Time": "2022-07-29T16:00:30.110181+00:00",
      "Rating": 4.44,
      "NumberOfRatings": 1035
    },
    {
      "Time": "2022-07-29T17:00:32.8852614+00:00",
      "Rating": 4.44,
      "NumberOfRatings": 1037
    },
    {
      "Time": "2022-07-30T05:00:28.3170511+00:00",
      "Rating": 4.43,
      "NumberOfRatings": 1054
    },
    {
      "Time": "2022-07-30T16:30:30.2017263+00:00",
      "Rating": 4.43,
      "NumberOfRatings": 1063
    },
    {
      "Time": "2022-07-31T06:00:30.9991331+00:00",
      "Rating": 4.43,
      "NumberOfRatings": 1077
    },
    {
      "Time": "2022-07-31T08:00:34.1668237+00:00",
      "Rating": 4.43,
      "NumberOfRatings": 1078
    },
    {
      "Time": "2022-07-31T09:31:23.9589907+00:00",
      "Rating": 4.43,
      "NumberOfRatings": 1081
    },
    {
      "Time": "2022-07-31T14:30:30.7319376+00:00",
      "Rating": 4.44,
      "NumberOfRatings": 1084
    }
  ],
  "Tags": [
    {
      "Text": "This game has Quickly Understood Controls",
      "Count": 24
    },
    {
      "Text": "This game has Diverse Characters",
      "Count": 27
    },
    {
      "Text": "This game has Amazing Storytelling",
      "Count": 25
    },
    {
      "Text": "This game is Extremely Fun",
      "Count": 21
    },
    {
      "Text": "This game is Highly Recommended",
      "Count": 21
    },
    {
      "Text": "This game has Amazing Characters",
      "Count": 22
    },
    {
      "Text": "This game is Educational",
      "Count": 20
    }
  ]
}