{
  "ID": "b671fbc7be424e888c9346a9a6d3d9db",
  "Name": "Celeste",
  "ProductSlug": "celeste/home",
  "Rating": 4.91,
  "NumberOfRatings": 1282,
  "FirstSeen": "2022-07-22T20:25:26.412797+00:00",
  "LastChanged": "2022-07-22T20:25:26.4127971+00:00",
  "RatingHistory": [
    {
      "Time": "2022-07-22T20:25:26.4127972+00:00",
      "Rating": 4.91,
      "NumberOfRatings": 1282
    }
  ],
  "Tags": [
    {
      "Text": "This game has Great Boss Battles",
      "Count": 313
    },
    {
      "Text": "This game has Quickly Understood Controls",
      "Count": 25
    },
    {
      "Text": "This game has Challenging Combat",
      "Count": 25
    },
    {
      "Text": "This game has Amazing Storytelling",
      "Count": 22
    },
    {
      "Text": "This game has Obsessive Gameplay",
      "Count": 20
    }
  ]
}