{
  "ID": "8518a041f3064613a354f997aac0c3cb",
  "Name": "Spiritfarer\u00AE: Farewell Edition",
  "Names": [],
  "Rating": 4.89,
  "NumberOfRatings": 132,
  "DailyRatings": 2.61,
  "FirstSeen": "2022-07-22T20:25:28.7454672+00:00",
  "LastChanged": "2022-08-08T22:01:21.1754729+00:00",
  "RatingHistory": [
    {
      "Time": "2022-07-22T20:25:28.7454676+00:00",
      "Rating": 4.87,
      "NumberOfRatings": 85
    },
    {
      "Time": "2022-07-23T10:10:08.4304802+00:00",
      "Rating": 4.88,
      "NumberOfRatings": 88
    },
    {
      "Time": "2022-07-23T16:01:26.8631658+00:00",
      "Rating": 4.88,
      "NumberOfRatings": 89
    },
    {
      "Time": "2022-07-24T16:02:14.1702991+00:00",
      "Rating": 4.88,
      "NumberOfRatings": 90
    },
    {
      "Time": "2022-07-26T10:01:48.5114655+00:00",
      "Rating": 4.88,
      "NumberOfRatings": 94
    },
    {
      "Time": "2022-07-27T08:01:21.8313603+00:00",
      "Rating": 4.88,
      "NumberOfRatings": 98
    },
    {
      "Time": "2022-07-27T16:01:43.7781263+00:00",
      "Rating": 4.88,
      "NumberOfRatings": 100
    },
    {
      "Time": "2022-07-29T06:31:17.0486892+00:00",
      "Rating": 4.88,
      "NumberOfRatings": 102
    },
    {
      "Time": "2022-07-29T23:31:21.0873731+00:00",
      "Rating": 4.89,
      "NumberOfRatings": 107
    },
    {
      "Time": "2022-07-30T16:31:34.8320489+00:00",
      "Rating": 4.89,
      "NumberOfRatings": 109
    },
    {
      "Time": "2022-07-31T10:32:36.3800747+00:00",
      "Rating": 4.88,
      "NumberOfRatings": 111
    },
    {
      "Time": "2022-08-01T10:32:31.5710197+00:00",
      "Rating": 4.88,
      "NumberOfRatings": 112
    },
    {
      "Time": "2022-08-01T13:31:20.2915058+00:00",
      "Rating": 4.88,
      "NumberOfRatings": 113
    },
    {
      "Time": "2022-08-02T09:31:23.6670267+00:00",
      "Rating": 4.89,
      "NumberOfRatings": 115
    },
    {
      "Time": "2022-08-03T03:31:19.9646803+00:00",
      "Rating": 4.88,
      "NumberOfRatings": 117
    },
    {
      "Time": "2022-08-04T06:01:20.717209+00:00",
      "Rating": 4.88,
      "NumberOfRatings": 119
    },
    {
      "Time": "2022-08-04T17:31:53.9989083+00:00",
      "Rating": 4.88,
      "NumberOfRatings": 121
    },
    {
      "Time": "2022-08-05T15:01:23.4815209+00:00",
      "Rating": 4.89,
      "NumberOfRatings": 124
    },
    {
      "Time": "2022-08-06T03:31:29.126924+00:00",
      "Rating": 4.89,
      "NumberOfRatings": 125
    },
    {
      "Time": "2022-08-06T13:31:21.8733966+00:00",
      "Rating": 4.89,
      "NumberOfRatings": 127
    },
    {
      "Time": "2022-08-07T13:31:35.6432033+00:00",
      "Rating": 4.89,
      "NumberOfRatings": 129
    },
    {
      "Time": "2022-08-07T22:01:21.7495214+00:00",
      "Rating": 4.89,
      "NumberOfRatings": 130
    },
    {
      "Time": "2022-08-08T22:01:21.175473+00:00",
      "Rating": 4.89,
      "NumberOfRatings": 132
    }
  ],
  "Tags": []
}