{
  "ID": "jaguar",
  "Name": "Subnautica",
  "Rating": 4.84,
  "NumberOfRatings": 7928,
  "FirstSeen": "2022-07-22T20:29:19.8641148+00:00",
  "LastChanged": "2022-10-14T17:02:15.6891175+00:00",
  "RatingHistory": [
    {
      "Time": "2022-07-22T20:29:19.864115+00:00",
      "Rating": 4.83,
      "NumberOfRatings": 3860
    },
    {
      "Time": "2022-07-23T00:05:26.1967989+00:00",
      "Rating": 4.84,
      "NumberOfRatings": 3869
    },
    {
      "Time": "2022-07-23T04:04:42.3822731+00:00",
      "Rating": 4.84,
      "NumberOfRatings": 3875
    },
    {
      "Time": "2022-07-23T10:02:55.5390367+00:00",
      "Rating": 4.83,
      "NumberOfRatings": 3890
    },
    {
      "Time": "2022-07-23T10:27:44.7279638+00:00",
      "Rating": 4.84,
      "NumberOfRatings": 3892
    },
    {
      "Time": "2022-07-23T13:06:14.3317664+00:00",
      "Rating": 4.84,
      "NumberOfRatings": 3900
    },
    {
      "Time": "2022-07-23T18:01:47.3010423+00:00",
      "Rating": 4.83,
      "NumberOfRatings": 3922
    },
    {
      "Time": "2022-07-23T20:01:46.3844037+00:00",
      "Rating": 4.83,
      "NumberOfRatings": 3931
    },
    {
      "Time": "2022-07-24T06:02:19.9154949+00:00",
      "Rating": 4.83,
      "NumberOfRatings": 3950
    },
    {
      "Time": "2022-07-24T08:01:48.4380779+00:00",
      "Rating": 4.83,
      "NumberOfRatings": 3961
    },
    {
      "Time": "2022-07-24T12:01:50.2938529+00:00",
      "Rating": 4.84,
      "NumberOfRatings": 3971
    },
    {
      "Time": "2022-07-24T14:02:20.2674373+00:00",
      "Rating": 4.84,
      "NumberOfRatings": 3988
    },
    {
      "Time": "2022-07-24T16:02:43.2509653+00:00",
      "Rating": 4.84,
      "NumberOfRatings": 3991
    },
    {
      "Time": "2022-07-24T18:01:50.5774119+00:00",
      "Rating": 4.83,
      "NumberOfRatings": 3995
    },
    {
      "Time": "2022-07-24T20:01:51.4566159+00:00",
      "Rating": 4.83,
      "NumberOfRatings": 4006
    },
    {
      "Time": "2022-07-24T22:01:48.4557755+00:00",
      "Rating": 4.83,
      "NumberOfRatings": 4008
    },
    {
      "Time": "2022-07-25T04:02:10.1484869+00:00",
      "Rating": 4.83,
      "NumberOfRatings": 4023
    },
    {
      "Time": "2022-07-25T10:02:15.5129952+00:00",
      "Rating": 4.84,
      "NumberOfRatings": 4037
    },
    {
      "Time": "2022-07-25T14:03:02.7999866+00:00",
      "Rating": 4.84,
      "NumberOfRatings": 4055
    },
    {
      "Time": "2022-07-25T16:02:29.7843788+00:00",
      "Rating": 4.84,
      "NumberOfRatings": 4058
    },
    {
      "Time": "2022-07-25T18:02:13.0470211+00:00",
      "Rating": 4.84,
      "NumberOfRatings": 4073
    },
    {
      "Time": "2022-07-25T22:01:50.1812414+00:00",
      "Rating": 4.84,
      "NumberOfRatings": 4084
    },
    {
      "Time": "2022-07-26T00:02:15.9139045+00:00",
      "Rating": 4.84,
      "NumberOfRatings": 4088
    },
    {
      "Time": "2022-07-26T04:02:25.6418138+00:00",
      "Rating": 4.84,
      "NumberOfRatings": 4095
    },
    {
      "Time": "2022-07-26T08:02:09.3007513+00:00",
      "Rating": 4.84,
      "NumberOfRatings": 4099
    },
    {
      "Time": "2022-07-26T12:02:20.3178096+00:00",
      "Rating": 4.84,
      "NumberOfRatings": 4104
    },
    {
      "Time": "2022-07-26T14:03:58.381025+00:00",
      "Rating": 4.84,
      "NumberOfRatings": 4126
    },
    {
      "Time": "2022-07-26T18:02:45.9810869+00:00",
      "Rating": 4.84,
      "NumberOfRatings": 4138
    },
    {
      "Time": "2022-07-26T20:02:24.355592+00:00",
      "Rating": 4.84,
      "NumberOfRatings": 4148
    },
    {
      "Time": "2022-07-27T00:01:56.4869472+00:00",
      "Rating": 4.84,
      "NumberOfRatings": 4168
    },
    {
      "Time": "2022-07-27T08:01:48.8298406+00:00",
      "Rating": 4.84,
      "NumberOfRatings": 4183
    },
    {
      "Time": "2022-07-27T10:02:07.9218542+00:00",
      "Rating": 4.84,
      "NumberOfRatings": 4184
    },
    {
      "Time": "2022-07-27T12:02:10.0175693+00:00",
      "Rating": 4.84,
      "NumberOfRatings": 4185
    },
    {
      "Time": "2022-07-27T14:02:22.0545196+00:00",
      "Rating": 4.84,
      "NumberOfRatings": 4190
    },
    {
      "Time": "2022-07-27T16:02:11.263687+00:00",
      "Rating": 4.84,
      "NumberOfRatings": 4197
    },
    {
      "Time": "2022-07-27T18:02:08.6573393+00:00",
      "Rating": 4.84,
      "NumberOfRatings": 4211
    },
    {
      "Time": "2022-07-27T22:02:06.0549152+00:00",
      "Rating": 4.84,
      "NumberOfRatings": 4222
    },
    {
      "Time": "2022-07-28T02:01:59.5062023+00:00",
      "Rating": 4.84,
      "NumberOfRatings": 4233
    },
    {
      "Time": "2022-07-28T10:02:10.9327966+00:00",
      "Rating": 4.84,
      "NumberOfRatings": 4242
    },
    {
      "Time": "2022-07-28T14:02:24.0747041+00:00",
      "Rating": 4.84,
      "NumberOfRatings": 4253
    },
    {
      "Time": "2022-07-28T20:31:52.9687384+00:00",
      "Rating": 4.84,
      "NumberOfRatings": 4279
    },
    {
      "Time": "2022-07-28T21:02:20.3830826+00:00",
      "Rating": 4.84,
      "NumberOfRatings": 4281
    },
    {
      "Time": "2022-07-28T22:31:41.8218696+00:00",
      "Rating": 4.84,
      "NumberOfRatings": 4287
    },
    {
      "Time": "2022-07-29T06:01:46.3048393+00:00",
      "Rating": 4.84,
      "NumberOfRatings": 4302
    },
    {
      "Time": "2022-07-29T11:01:55.0167491+00:00",
      "Rating": 4.84,
      "NumberOfRatings": 4309
    },
    {
      "Time": "2022-07-29T13:32:16.7669895+00:00",
      "Rating": 4.84,
      "NumberOfRatings": 4315
    },
    {
      "Time": "2022-07-29T15:01:50.7373217+00:00",
      "Rating": 4.84,
      "NumberOfRatings": 4324
    },
    {
      "Time": "2022-07-29T18:31:47.6951285+00:00",
      "Rating": 4.84,
      "NumberOfRatings": 4342
    },
    {
      "Time": "2022-07-29T19:32:15.2787334+00:00",
      "Rating": 4.84,
      "NumberOfRatings": 4350
    },
    {
      "Time": "2022-07-29T20:32:01.0131229+00:00",
      "Rating": 4.84,
      "NumberOfRatings": 4360
    },
    {
      "Time": "2022-07-29T22:31:49.3858643+00:00",
      "Rating": 4.84,
      "NumberOfRatings": 4367
    },
    {
      "Time": "2022-07-30T00:31:44.8116613+00:00",
      "Rating": 4.84,
      "NumberOfRatings": 4379
    },
    {
      "Time": "2022-07-30T07:31:46.9171604+00:00",
      "Rating": 4.84,
      "NumberOfRatings": 4398
    },
    {
      "Time": "2022-07-30T16:32:07.5698504+00:00",
      "Rating": 4.84,
      "NumberOfRatings": 4420
    },
    {
      "Time": "2022-07-30T17:32:12.0518384+00:00",
      "Rating": 4.84,
      "NumberOfRatings": 4423
    },
    {
      "Time": "2022-07-30T19:02:15.4786215+00:00",
      "Rating": 4.84,
      "NumberOfRatings": 4428
    },
    {
      "Time": "2022-07-30T20:02:16.0645343+00:00",
      "Rating": 4.84,
      "NumberOfRatings": 4434
    },
    {
      "Time": "2022-07-30T22:31:59.8485371+00:00",
      "Rating": 4.84,
      "NumberOfRatings": 4440
    },
    {
      "Time": "2022-07-31T01:01:47.0626781+00:00",
      "Rating": 4.84,
      "NumberOfRatings": 4449
    },
    {
      "Time": "2022-07-31T06:31:43.8356362+00:00",
      "Rating": 4.84,
      "NumberOfRatings": 4457
    },
    {
      "Time": "2022-07-31T10:01:49.6889252+00:00",
      "Rating": 4.84,
      "NumberOfRatings": 4465
    },
    {
      "Time": "2022-07-31T13:31:55.8354622+00:00",
      "Rating": 4.84,
      "NumberOfRatings": 4470
    },
    {
      "Time": "2022-07-31T17:31:50.7717195+00:00",
      "Rating": 4.84,
      "NumberOfRatings": 4487
    },
    {
      "Time": "2022-07-31T23:31:51.8894184+00:00",
      "Rating": 4.84,
      "NumberOfRatings": 4515
    },
    {
      "Time": "2022-08-01T01:31:44.673318+00:00",
      "Rating": 4.84,
      "NumberOfRatings": 4522
    },
    {
      "Time": "2022-08-01T06:31:53.0501827+00:00",
      "Rating": 4.84,
      "NumberOfRatings": 4532
    },
    {
      "Time": "2022-08-01T09:02:21.2854532+00:00",
      "Rating": 4.84,
      "NumberOfRatings": 4536
    },
    {
      "Time": "2022-08-01T10:01:50.8938466+00:00",
      "Rating": 4.84,
      "NumberOfRatings": 4541
    },
    {
      "Time": "2022-08-01T12:31:50.5147137+00:00",
      "Rating": 4.84,
      "NumberOfRatings": 4546
    },
    {
      "Time": "2022-08-01T13:31:46.9272541+00:00",
      "Rating": 4.84,
      "NumberOfRatings": 4549
    },
    {
      "Time": "2022-08-01T16:01:56.033535+00:00",
      "Rating": 4.84,
      "NumberOfRatings": 4560
    },
    {
      "Time": "2022-08-01T17:31:48.0830561+00:00",
      "Rating": 4.83,
      "NumberOfRatings": 4566
    },
    {
      "Time": "2022-08-01T18:01:51.9125724+00:00",
      "Rating": 4.83,
      "NumberOfRatings": 4570
    },
    {
      "Time": "2022-08-01T21:01:50.0277679+00:00",
      "Rating": 4.83,
      "NumberOfRatings": 4576
    },
    {
      "Time": "2022-08-01T21:31:44.684049+00:00",
      "Rating": 4.83,
      "NumberOfRatings": 4581
    },
    {
      "Time": "2022-08-02T03:01:47.9018732+00:00",
      "Rating": 4.83,
      "NumberOfRatings": 4588
    },
    {
      "Time": "2022-08-02T07:02:48.3000529+00:00",
      "Rating": 4.83,
      "NumberOfRatings": 4595
    },
    {
      "Time": "2022-08-02T12:31:47.5189632+00:00",
      "Rating": 4.83,
      "NumberOfRatings": 4605
    },
    {
      "Time": "2022-08-02T14:31:54.8364548+00:00",
      "Rating": 4.83,
      "NumberOfRatings": 4612
    },
    {
      "Time": "2022-08-02T16:01:51.7568963+00:00",
      "Rating": 4.83,
      "NumberOfRatings": 4618
    },
    {
      "Time": "2022-08-02T17:01:57.7674489+00:00",
      "Rating": 4.83,
      "NumberOfRatings": 4623
    },
    {
      "Time": "2022-08-02T18:31:53.7693376+00:00",
      "Rating": 4.83,
      "NumberOfRatings": 4631
    },
    {
      "Time": "2022-08-02T20:01:51.7232969+00:00",
      "Rating": 4.83,
      "NumberOfRatings": 4636
    },
    {
      "Time": "2022-08-02T21:01:54.0617501+00:00",
      "Rating": 4.83,
      "NumberOfRatings": 4644
    },
    {
      "Time": "2022-08-03T03:31:49.8427202+00:00",
      "Rating": 4.83,
      "NumberOfRatings": 4656
    },
    {
      "Time": "2022-08-03T05:31:52.2709645+00:00",
      "Rating": 4.83,
      "NumberOfRatings": 4657
    },
    {
      "Time": "2022-08-03T14:02:21.3908444+00:00",
      "Rating": 4.83,
      "NumberOfRatings": 4677
    },
    {
      "Time": "2022-08-03T18:32:08.8214323+00:00",
      "Rating": 4.83,
      "NumberOfRatings": 4695
    },
    {
      "Time": "2022-08-03T19:02:14.9541089+00:00",
      "Rating": 4.83,
      "NumberOfRatings": 4697
    },
    {
      "Time": "2022-08-03T21:01:58.1194224+00:00",
      "Rating": 4.83,
      "NumberOfRatings": 4701
    },
    {
      "Time": "2022-08-03T22:31:46.702126+00:00",
      "Rating": 4.83,
      "NumberOfRatings": 4707
    },
    {
      "Time": "2022-08-04T00:31:44.1055992+00:00",
      "Rating": 4.83,
      "NumberOfRatings": 4714
    },
    {
      "Time": "2022-08-04T02:31:52.4085215+00:00",
      "Rating": 4.83,
      "NumberOfRatings": 4718
    },
    {
      "Time": "2022-08-04T07:31:48.3500256+00:00",
      "Rating": 4.83,
      "NumberOfRatings": 4726
    },
    {
      "Time": "2022-08-04T10:01:48.3034297+00:00",
      "Rating": 4.83,
      "NumberOfRatings": 4730
    },
    {
      "Time": "2022-08-04T11:01:57.2985362+00:00",
      "Rating": 4.83,
      "NumberOfRatings": 4731
    },
    {
      "Time": "2022-08-04T20:01:49.8540724+00:00",
      "Rating": 4.83,
      "NumberOfRatings": 4781
    },
    {
      "Time": "2022-08-04T21:31:46.2486756+00:00",
      "Rating": 4.83,
      "NumberOfRatings": 4787
    },
    {
      "Time": "2022-08-05T01:01:50.2769051+00:00",
      "Rating": 4.83,
      "NumberOfRatings": 4797
    },
    {
      "Time": "2022-08-05T02:02:44.5027394+00:00",
      "Rating": 4.83,
      "NumberOfRatings": 4802
    },
    {
      "Time": "2022-08-05T03:01:48.655049+00:00",
      "Rating": 4.83,
      "NumberOfRatings": 4803
    },
    {
      "Time": "2022-08-05T09:01:49.9666355+00:00",
      "Rating": 4.83,
      "NumberOfRatings": 4813
    },
    {
      "Time": "2022-08-05T10:02:13.8612717+00:00",
      "Rating": 4.83,
      "NumberOfRatings": 4814
    },
    {
      "Time": "2022-08-05T12:31:52.0523134+00:00",
      "Rating": 4.83,
      "NumberOfRatings": 4824
    },
    {
      "Time": "2022-08-05T14:31:48.6835365+00:00",
      "Rating": 4.83,
      "NumberOfRatings": 4827
    },
    {
      "Time": "2022-08-05T16:02:40.2052261+00:00",
      "Rating": 4.83,
      "NumberOfRatings": 4832
    },
    {
      "Time": "2022-08-05T16:31:49.1604697+00:00",
      "Rating": 4.83,
      "NumberOfRatings": 4836
    },
    {
      "Time": "2022-08-05T18:02:24.3575641+00:00",
      "Rating": 4.83,
      "NumberOfRatings": 4841
    },
    {
      "Time": "2022-08-05T20:01:54.7643912+00:00",
      "Rating": 4.83,
      "NumberOfRatings": 4855
    },
    {
      "Time": "2022-08-05T21:02:00.5489081+00:00",
      "Rating": 4.83,
      "NumberOfRatings": 4868
    },
    {
      "Time": "2022-08-06T02:32:02.2815745+00:00",
      "Rating": 4.83,
      "NumberOfRatings": 4891
    },
    {
      "Time": "2022-08-06T03:01:48.4128203+00:00",
      "Rating": 4.83,
      "NumberOfRatings": 4892
    },
    {
      "Time": "2022-08-06T11:01:59.307948+00:00",
      "Rating": 4.83,
      "NumberOfRatings": 4918
    },
    {
      "Time": "2022-08-06T12:01:48.4093277+00:00",
      "Rating": 4.83,
      "NumberOfRatings": 4924
    },
    {
      "Time": "2022-08-06T17:31:55.0013145+00:00",
      "Rating": 4.83,
      "NumberOfRatings": 4942
    },
    {
      "Time": "2022-08-06T18:01:52.6452784+00:00",
      "Rating": 4.83,
      "NumberOfRatings": 4943
    },
    {
      "Time": "2022-08-06T19:01:49.3062945+00:00",
      "Rating": 4.83,
      "NumberOfRatings": 4945
    },
    {
      "Time": "2022-08-06T20:01:50.0920049+00:00",
      "Rating": 4.83,
      "NumberOfRatings": 4948
    },
    {
      "Time": "2022-08-06T21:01:50.2253707+00:00",
      "Rating": 4.83,
      "NumberOfRatings": 4951
    },
    {
      "Time": "2022-08-07T04:01:51.3910302+00:00",
      "Rating": 4.83,
      "NumberOfRatings": 4965
    },
    {
      "Time": "2022-08-07T04:31:50.7698228+00:00",
      "Rating": 4.83,
      "NumberOfRatings": 4967
    },
    {
      "Time": "2022-08-07T07:31:55.1506167+00:00",
      "Rating": 4.83,
      "NumberOfRatings": 4969
    },
    {
      "Time": "2022-08-07T11:02:09.3179672+00:00",
      "Rating": 4.83,
      "NumberOfRatings": 4976
    },
    {
      "Time": "2022-08-07T11:32:12.5564783+00:00",
      "Rating": 4.83,
      "NumberOfRatings": 4981
    },
    {
      "Time": "2022-08-07T13:02:07.7924729+00:00",
      "Rating": 4.83,
      "NumberOfRatings": 4985
    },
    {
      "Time": "2022-08-07T20:01:52.9894912+00:00",
      "Rating": 4.83,
      "NumberOfRatings": 5013
    },
    {
      "Time": "2022-08-07T21:31:45.8660797+00:00",
      "Rating": 4.83,
      "NumberOfRatings": 5016
    },
    {
      "Time": "2022-08-07T23:31:47.0345597+00:00",
      "Rating": 4.83,
      "NumberOfRatings": 5024
    },
    {
      "Time": "2022-08-08T01:01:50.438732+00:00",
      "Rating": 4.83,
      "NumberOfRatings": 5031
    },
    {
      "Time": "2022-08-08T03:01:46.0879375+00:00",
      "Rating": 4.83,
      "NumberOfRatings": 5035
    },
    {
      "Time": "2022-08-08T10:01:49.8793479+00:00",
      "Rating": 4.83,
      "NumberOfRatings": 5049
    },
    {
      "Time": "2022-08-08T12:01:52.5870405+00:00",
      "Rating": 4.83,
      "NumberOfRatings": 5054
    },
    {
      "Time": "2022-08-08T14:01:53.062399+00:00",
      "Rating": 4.83,
      "NumberOfRatings": 5061
    },
    {
      "Time": "2022-08-08T14:31:51.969848+00:00",
      "Rating": 4.83,
      "NumberOfRatings": 5062
    },
    {
      "Time": "2022-08-08T16:02:55.7665333+00:00",
      "Rating": 4.83,
      "NumberOfRatings": 5065
    },
    {
      "Time": "2022-08-08T17:33:40.3053327+00:00",
      "Rating": 4.83,
      "NumberOfRatings": 5067
    },
    {
      "Time": "2022-08-08T20:02:35.8059524+00:00",
      "Rating": 4.83,
      "NumberOfRatings": 5079
    },
    {
      "Time": "2022-08-08T23:31:51.3495201+00:00",
      "Rating": 4.83,
      "NumberOfRatings": 5086
    },
    {
      "Time": "2022-08-09T04:01:55.5325763+00:00",
      "Rating": 4.83,
      "NumberOfRatings": 5098
    },
    {
      "Time": "2022-08-09T13:02:09.1895111+00:00",
      "Rating": 4.83,
      "NumberOfRatings": 5112
    },
    {
      "Time": "2022-08-09T15:02:53.9488343+00:00",
      "Rating": 4.83,
      "NumberOfRatings": 5121
    },
    {
      "Time": "2022-08-09T19:01:54.7217023+00:00",
      "Rating": 4.83,
      "NumberOfRatings": 5129
    },
    {
      "Time": "2022-08-09T20:01:58.8794021+00:00",
      "Rating": 4.83,
      "NumberOfRatings": 5136
    },
    {
      "Time": "2022-08-09T21:01:55.458098+00:00",
      "Rating": 4.83,
      "NumberOfRatings": 5142
    },
    {
      "Time": "2022-08-09T22:32:20.9243274+00:00",
      "Rating": 4.83,
      "NumberOfRatings": 5147
    },
    {
      "Time": "2022-08-10T01:31:49.9231426+00:00",
      "Rating": 4.83,
      "NumberOfRatings": 5156
    },
    {
      "Time": "2022-08-10T03:32:22.9709082+00:00",
      "Rating": 4.83,
      "NumberOfRatings": 5164
    },
    {
      "Time": "2022-08-10T07:01:54.8554018+00:00",
      "Rating": 4.83,
      "NumberOfRatings": 5169
    },
    {
      "Time": "2022-08-10T10:02:04.6746438+00:00",
      "Rating": 4.83,
      "NumberOfRatings": 5178
    },
    {
      "Time": "2022-08-10T14:31:51.7237076+00:00",
      "Rating": 4.83,
      "NumberOfRatings": 5191
    },
    {
      "Time": "2022-08-10T16:02:46.9594762+00:00",
      "Rating": 4.83,
      "NumberOfRatings": 5193
    },
    {
      "Time": "2022-08-10T18:02:30.6410147+00:00",
      "Rating": 4.83,
      "NumberOfRatings": 5198
    },
    {
      "Time": "2022-08-10T19:02:25.8993174+00:00",
      "Rating": 4.83,
      "NumberOfRatings": 5204
    },
    {
      "Time": "2022-08-10T21:01:52.1808977+00:00",
      "Rating": 4.83,
      "NumberOfRatings": 5213
    },
    {
      "Time": "2022-08-10T23:02:23.9663247+00:00",
      "Rating": 4.83,
      "NumberOfRatings": 5218
    },
    {
      "Time": "2022-08-11T03:01:54.2404294+00:00",
      "Rating": 4.83,
      "NumberOfRatings": 5225
    },
    {
      "Time": "2022-08-11T07:32:08.1222009+00:00",
      "Rating": 4.83,
      "NumberOfRatings": 5228
    },
    {
      "Time": "2022-08-11T08:32:45.6080392+00:00",
      "Rating": 4.83,
      "NumberOfRatings": 5229
    },
    {
      "Time": "2022-08-11T09:02:15.8623432+00:00",
      "Rating": 4.83,
      "NumberOfRatings": 5234
    },
    {
      "Time": "2022-08-11T10:02:22.0011762+00:00",
      "Rating": 4.83,
      "NumberOfRatings": 5236
    },
    {
      "Time": "2022-08-11T14:32:20.5088522+00:00",
      "Rating": 4.83,
      "NumberOfRatings": 5244
    },
    {
      "Time": "2022-08-11T18:02:24.325548+00:00",
      "Rating": 4.83,
      "NumberOfRatings": 5267
    },
    {
      "Time": "2022-08-11T19:32:07.0223458+00:00",
      "Rating": 4.83,
      "NumberOfRatings": 5271
    },
    {
      "Time": "2022-08-11T20:02:15.0059031+00:00",
      "Rating": 4.83,
      "NumberOfRatings": 5275
    },
    {
      "Time": "2022-08-11T23:32:31.3527207+00:00",
      "Rating": 4.83,
      "NumberOfRatings": 5278
    },
    {
      "Time": "2022-08-12T00:31:45.953168+00:00",
      "Rating": 4.83,
      "NumberOfRatings": 5286
    },
    {
      "Time": "2022-08-12T02:32:20.9487677+00:00",
      "Rating": 4.83,
      "NumberOfRatings": 5292
    },
    {
      "Time": "2022-08-12T04:01:54.10303+00:00",
      "Rating": 4.83,
      "NumberOfRatings": 5299
    },
    {
      "Time": "2022-08-12T08:03:21.0726316+00:00",
      "Rating": 4.83,
      "NumberOfRatings": 5306
    },
    {
      "Time": "2022-08-12T11:31:51.0428013+00:00",
      "Rating": 4.83,
      "NumberOfRatings": 5313
    },
    {
      "Time": "2022-08-12T18:32:00.1559122+00:00",
      "Rating": 4.83,
      "NumberOfRatings": 5335
    },
    {
      "Time": "2022-08-12T19:01:53.7084574+00:00",
      "Rating": 4.83,
      "NumberOfRatings": 5337
    },
    {
      "Time": "2022-08-12T20:32:45.7879284+00:00",
      "Rating": 4.83,
      "NumberOfRatings": 5342
    },
    {
      "Time": "2022-08-12T21:32:08.12951+00:00",
      "Rating": 4.83,
      "NumberOfRatings": 5346
    },
    {
      "Time": "2022-08-12T23:02:39.6760327+00:00",
      "Rating": 4.83,
      "NumberOfRatings": 5354
    },
    {
      "Time": "2022-08-13T00:02:51.5095318+00:00",
      "Rating": 4.83,
      "NumberOfRatings": 5355
    },
    {
      "Time": "2022-08-13T01:31:58.4546714+00:00",
      "Rating": 4.83,
      "NumberOfRatings": 5358
    },
    {
      "Time": "2022-08-13T03:01:51.3873769+00:00",
      "Rating": 4.83,
      "NumberOfRatings": 5359
    },
    {
      "Time": "2022-08-13T08:31:51.5260788+00:00",
      "Rating": 4.83,
      "NumberOfRatings": 5367
    },
    {
      "Time": "2022-08-13T12:31:48.3508378+00:00",
      "Rating": 4.83,
      "NumberOfRatings": 5377
    },
    {
      "Time": "2022-08-13T13:31:49.9418565+00:00",
      "Rating": 4.83,
      "NumberOfRatings": 5380
    },
    {
      "Time": "2022-08-13T14:31:53.1103266+00:00",
      "Rating": 4.83,
      "NumberOfRatings": 5383
    },
    {
      "Time": "2022-08-13T16:31:46.6551071+00:00",
      "Rating": 4.83,
      "NumberOfRatings": 5395
    },
    {
      "Time": "2022-08-13T19:31:50.7844245+00:00",
      "Rating": 4.83,
      "NumberOfRatings": 5410
    },
    {
      "Time": "2022-08-14T03:01:51.9559525+00:00",
      "Rating": 4.83,
      "NumberOfRatings": 5439
    },
    {
      "Time": "2022-08-14T04:31:49.2551681+00:00",
      "Rating": 4.83,
      "NumberOfRatings": 5440
    },
    {
      "Time": "2022-08-14T05:31:52.4690491+00:00",
      "Rating": 4.83,
      "NumberOfRatings": 5442
    },
    {
      "Time": "2022-08-14T08:01:52.6293377+00:00",
      "Rating": 4.83,
      "NumberOfRatings": 5444
    },
    {
      "Time": "2022-08-14T09:01:55.3522604+00:00",
      "Rating": 4.83,
      "NumberOfRatings": 5446
    },
    {
      "Time": "2022-08-14T11:31:49.5759962+00:00",
      "Rating": 4.83,
      "NumberOfRatings": 5451
    },
    {
      "Time": "2022-08-14T14:01:58.4936781+00:00",
      "Rating": 4.83,
      "NumberOfRatings": 5458
    },
    {
      "Time": "2022-08-14T16:01:54.9861246+00:00",
      "Rating": 4.83,
      "NumberOfRatings": 5463
    },
    {
      "Time": "2022-08-14T17:01:55.5789748+00:00",
      "Rating": 4.83,
      "NumberOfRatings": 5466
    },
    {
      "Time": "2022-08-14T20:31:54.6334419+00:00",
      "Rating": 4.83,
      "NumberOfRatings": 5483
    },
    {
      "Time": "2022-08-14T22:01:52.9920838+00:00",
      "Rating": 4.83,
      "NumberOfRatings": 5487
    },
    {
      "Time": "2022-08-15T00:02:01.9021994+00:00",
      "Rating": 4.83,
      "NumberOfRatings": 5490
    },
    {
      "Time": "2022-08-15T06:02:00.4154487+00:00",
      "Rating": 4.83,
      "NumberOfRatings": 5506
    },
    {
      "Time": "2022-08-15T11:32:29.036422+00:00",
      "Rating": 4.83,
      "NumberOfRatings": 5514
    },
    {
      "Time": "2022-08-15T12:02:19.1555098+00:00",
      "Rating": 4.83,
      "NumberOfRatings": 5516
    },
    {
      "Time": "2022-08-15T14:32:37.8728882+00:00",
      "Rating": 4.83,
      "NumberOfRatings": 5520
    },
    {
      "Time": "2022-08-15T15:02:01.4639523+00:00",
      "Rating": 4.83,
      "NumberOfRatings": 5522
    },
    {
      "Time": "2022-08-15T17:32:49.3111934+00:00",
      "Rating": 4.83,
      "NumberOfRatings": 5534
    },
    {
      "Time": "2022-08-15T18:31:47.2697966+00:00",
      "Rating": 4.83,
      "NumberOfRatings": 5537
    },
    {
      "Time": "2022-08-15T20:01:48.8036099+00:00",
      "Rating": 4.83,
      "NumberOfRatings": 5548
    },
    {
      "Time": "2022-08-16T04:31:44.9249763+00:00",
      "Rating": 4.83,
      "NumberOfRatings": 5565
    },
    {
      "Time": "2022-08-16T10:02:28.0803899+00:00",
      "Rating": 4.83,
      "NumberOfRatings": 5582
    },
    {
      "Time": "2022-08-16T13:02:21.5692332+00:00",
      "Rating": 4.83,
      "NumberOfRatings": 5588
    },
    {
      "Time": "2022-08-16T16:02:22.455367+00:00",
      "Rating": 4.83,
      "NumberOfRatings": 5600
    },
    {
      "Time": "2022-08-16T18:02:29.0524428+00:00",
      "Rating": 4.83,
      "NumberOfRatings": 5605
    },
    {
      "Time": "2022-08-16T19:32:47.6267096+00:00",
      "Rating": 4.83,
      "NumberOfRatings": 5606
    },
    {
      "Time": "2022-08-16T22:02:13.6705099+00:00",
      "Rating": 4.83,
      "NumberOfRatings": 5616
    },
    {
      "Time": "2022-08-17T01:02:07.7969039+00:00",
      "Rating": 4.83,
      "NumberOfRatings": 5623
    },
    {
      "Time": "2022-08-17T06:31:47.2978905+00:00",
      "Rating": 4.83,
      "NumberOfRatings": 5629
    },
    {
      "Time": "2022-08-17T09:02:20.6263707+00:00",
      "Rating": 4.83,
      "NumberOfRatings": 5633
    },
    {
      "Time": "2022-08-17T10:31:52.7441424+00:00",
      "Rating": 4.83,
      "NumberOfRatings": 5636
    },
    {
      "Time": "2022-08-17T13:32:44.5097155+00:00",
      "Rating": 4.83,
      "NumberOfRatings": 5645
    },
    {
      "Time": "2022-08-17T15:02:07.3758773+00:00",
      "Rating": 4.83,
      "NumberOfRatings": 5648
    },
    {
      "Time": "2022-08-17T17:01:50.4919521+00:00",
      "Rating": 4.83,
      "NumberOfRatings": 5655
    },
    {
      "Time": "2022-08-17T19:32:02.2215041+00:00",
      "Rating": 4.83,
      "NumberOfRatings": 5663
    },
    {
      "Time": "2022-08-17T20:31:52.8545724+00:00",
      "Rating": 4.83,
      "NumberOfRatings": 5664
    },
    {
      "Time": "2022-08-17T22:02:24.9895372+00:00",
      "Rating": 4.83,
      "NumberOfRatings": 5671
    },
    {
      "Time": "2022-08-18T02:31:47.9398274+00:00",
      "Rating": 4.83,
      "NumberOfRatings": 5676
    },
    {
      "Time": "2022-08-18T13:31:53.5304494+00:00",
      "Rating": 4.83,
      "NumberOfRatings": 5702
    },
    {
      "Time": "2022-08-18T15:31:56.5063121+00:00",
      "Rating": 4.83,
      "NumberOfRatings": 5707
    },
    {
      "Time": "2022-08-18T16:02:39.7388272+00:00",
      "Rating": 4.83,
      "NumberOfRatings": 5708
    },
    {
      "Time": "2022-08-18T17:01:58.6233651+00:00",
      "Rating": 4.83,
      "NumberOfRatings": 5712
    },
    {
      "Time": "2022-08-18T20:02:37.8138475+00:00",
      "Rating": 4.83,
      "NumberOfRatings": 5724
    },
    {
      "Time": "2022-08-18T20:32:28.1299351+00:00",
      "Rating": 4.83,
      "NumberOfRatings": 5726
    },
    {
      "Time": "2022-08-18T22:02:44.5195334+00:00",
      "Rating": 4.83,
      "NumberOfRatings": 5727
    },
    {
      "Time": "2022-08-18T22:32:01.431255+00:00",
      "Rating": 4.83,
      "NumberOfRatings": 5735
    },
    {
      "Time": "2022-08-19T00:31:57.7663746+00:00",
      "Rating": 4.83,
      "NumberOfRatings": 5747
    },
    {
      "Time": "2022-08-19T02:32:07.3451294+00:00",
      "Rating": 4.83,
      "NumberOfRatings": 5749
    },
    {
      "Time": "2022-08-19T09:02:59.2079253+00:00",
      "Rating": 4.83,
      "NumberOfRatings": 5757
    },
    {
      "Time": "2022-08-19T18:02:11.6352837+00:00",
      "Rating": 4.83,
      "NumberOfRatings": 5778
    },
    {
      "Time": "2022-08-19T21:32:15.491579+00:00",
      "Rating": 4.83,
      "NumberOfRatings": 5798
    },
    {
      "Time": "2022-08-20T02:31:56.616584+00:00",
      "Rating": 4.83,
      "NumberOfRatings": 5808
    },
    {
      "Time": "2022-08-20T03:01:54.6412461+00:00",
      "Rating": 4.83,
      "NumberOfRatings": 5809
    },
    {
      "Time": "2022-08-20T08:02:12.7445122+00:00",
      "Rating": 4.83,
      "NumberOfRatings": 5814
    },
    {
      "Time": "2022-08-20T09:31:50.3063487+00:00",
      "Rating": 4.83,
      "NumberOfRatings": 5816
    },
    {
      "Time": "2022-08-20T11:02:02.208305+00:00",
      "Rating": 4.83,
      "NumberOfRatings": 5822
    },
    {
      "Time": "2022-08-20T15:01:53.1235462+00:00",
      "Rating": 4.83,
      "NumberOfRatings": 5838
    },
    {
      "Time": "2022-08-20T18:02:07.0729895+00:00",
      "Rating": 4.83,
      "NumberOfRatings": 5853
    },
    {
      "Time": "2022-08-20T21:31:54.8279545+00:00",
      "Rating": 4.83,
      "NumberOfRatings": 5866
    },
    {
      "Time": "2022-08-20T22:01:50.0789091+00:00",
      "Rating": 4.83,
      "NumberOfRatings": 5870
    },
    {
      "Time": "2022-08-21T01:01:55.4624966+00:00",
      "Rating": 4.83,
      "NumberOfRatings": 5875
    },
    {
      "Time": "2022-08-21T08:01:55.3475197+00:00",
      "Rating": 4.83,
      "NumberOfRatings": 5883
    },
    {
      "Time": "2022-08-21T09:32:01.3189728+00:00",
      "Rating": 4.83,
      "NumberOfRatings": 5886
    },
    {
      "Time": "2022-08-21T12:31:51.2477358+00:00",
      "Rating": 4.83,
      "NumberOfRatings": 5900
    },
    {
      "Time": "2022-08-21T16:01:55.8941345+00:00",
      "Rating": 4.83,
      "NumberOfRatings": 5908
    },
    {
      "Time": "2022-08-21T17:32:18.0663087+00:00",
      "Rating": 4.83,
      "NumberOfRatings": 5914
    },
    {
      "Time": "2022-08-22T02:31:53.1499897+00:00",
      "Rating": 4.83,
      "NumberOfRatings": 5949
    },
    {
      "Time": "2022-08-22T07:32:10.470136+00:00",
      "Rating": 4.83,
      "NumberOfRatings": 5955
    },
    {
      "Time": "2022-08-22T09:02:13.8959399+00:00",
      "Rating": 4.83,
      "NumberOfRatings": 5960
    },
    {
      "Time": "2022-08-22T09:31:59.5910442+00:00",
      "Rating": 4.83,
      "NumberOfRatings": 5963
    },
    {
      "Time": "2022-08-22T12:31:53.0986822+00:00",
      "Rating": 4.83,
      "NumberOfRatings": 5969
    },
    {
      "Time": "2022-08-22T16:31:56.6544991+00:00",
      "Rating": 4.83,
      "NumberOfRatings": 5982
    },
    {
      "Time": "2022-08-22T19:32:29.2662445+00:00",
      "Rating": 4.83,
      "NumberOfRatings": 5991
    },
    {
      "Time": "2022-08-22T20:32:41.1498895+00:00",
      "Rating": 4.83,
      "NumberOfRatings": 5996
    },
    {
      "Time": "2022-08-22T22:02:10.773495+00:00",
      "Rating": 4.83,
      "NumberOfRatings": 6000
    },
    {
      "Time": "2022-08-22T23:02:47.2176644+00:00",
      "Rating": 4.83,
      "NumberOfRatings": 6003
    },
    {
      "Time": "2022-08-23T09:02:19.2254902+00:00",
      "Rating": 4.83,
      "NumberOfRatings": 6023
    },
    {
      "Time": "2022-08-23T11:02:09.1730675+00:00",
      "Rating": 4.83,
      "NumberOfRatings": 6029
    },
    {
      "Time": "2022-08-23T14:32:22.5622346+00:00",
      "Rating": 4.83,
      "NumberOfRatings": 6038
    },
    {
      "Time": "2022-08-23T19:31:56.0094412+00:00",
      "Rating": 4.83,
      "NumberOfRatings": 6054
    },
    {
      "Time": "2022-08-23T21:02:36.6219043+00:00",
      "Rating": 4.83,
      "NumberOfRatings": 6056
    },
    {
      "Time": "2022-08-23T22:01:57.6193486+00:00",
      "Rating": 4.83,
      "NumberOfRatings": 6062
    },
    {
      "Time": "2022-08-23T23:31:54.3306624+00:00",
      "Rating": 4.83,
      "NumberOfRatings": 6068
    },
    {
      "Time": "2022-08-24T08:31:51.4957008+00:00",
      "Rating": 4.83,
      "NumberOfRatings": 6092
    },
    {
      "Time": "2022-08-24T09:32:27.3121106+00:00",
      "Rating": 4.83,
      "NumberOfRatings": 6095
    },
    {
      "Time": "2022-08-24T11:02:19.062547+00:00",
      "Rating": 4.83,
      "NumberOfRatings": 6099
    },
    {
      "Time": "2022-08-24T13:02:39.8651753+00:00",
      "Rating": 4.83,
      "NumberOfRatings": 6108
    },
    {
      "Time": "2022-08-24T17:01:57.5890157+00:00",
      "Rating": 4.83,
      "NumberOfRatings": 6121
    },
    {
      "Time": "2022-08-24T19:32:39.0450051+00:00",
      "Rating": 4.83,
      "NumberOfRatings": 6140
    },
    {
      "Time": "2022-08-24T21:31:58.4099294+00:00",
      "Rating": 4.83,
      "NumberOfRatings": 6145
    },
    {
      "Time": "2022-08-25T04:02:09.7004121+00:00",
      "Rating": 4.83,
      "NumberOfRatings": 6152
    },
    {
      "Time": "2022-08-25T04:31:56.9899829+00:00",
      "Rating": 4.83,
      "NumberOfRatings": 6153
    },
    {
      "Time": "2022-08-25T08:32:59.0926474+00:00",
      "Rating": 4.83,
      "NumberOfRatings": 6156
    },
    {
      "Time": "2022-08-25T09:01:57.8991548+00:00",
      "Rating": 4.83,
      "NumberOfRatings": 6161
    },
    {
      "Time": "2022-08-25T13:02:27.310143+00:00",
      "Rating": 4.83,
      "NumberOfRatings": 6168
    },
    {
      "Time": "2022-08-25T14:03:11.1745546+00:00",
      "Rating": 4.83,
      "NumberOfRatings": 6172
    },
    {
      "Time": "2022-08-25T14:32:31.1821202+00:00",
      "Rating": 4.83,
      "NumberOfRatings": 6174
    },
    {
      "Time": "2022-08-25T17:32:04.3835674+00:00",
      "Rating": 4.83,
      "NumberOfRatings": 6186
    },
    {
      "Time": "2022-08-25T19:31:55.7108033+00:00",
      "Rating": 4.83,
      "NumberOfRatings": 6198
    },
    {
      "Time": "2022-08-25T21:02:14.1683606+00:00",
      "Rating": 4.83,
      "NumberOfRatings": 6200
    },
    {
      "Time": "2022-08-26T02:31:55.5367472+00:00",
      "Rating": 4.83,
      "NumberOfRatings": 6211
    },
    {
      "Time": "2022-08-26T04:32:07.087017+00:00",
      "Rating": 4.83,
      "NumberOfRatings": 6214
    },
    {
      "Time": "2022-08-26T10:31:58.7304076+00:00",
      "Rating": 4.83,
      "NumberOfRatings": 6223
    },
    {
      "Time": "2022-08-26T14:32:07.4591971+00:00",
      "Rating": 4.83,
      "NumberOfRatings": 6241
    },
    {
      "Time": "2022-08-26T17:32:24.7022111+00:00",
      "Rating": 4.83,
      "NumberOfRatings": 6257
    },
    {
      "Time": "2022-08-26T21:32:10.9525526+00:00",
      "Rating": 4.83,
      "NumberOfRatings": 6289
    },
    {
      "Time": "2022-08-27T01:02:17.9100347+00:00",
      "Rating": 4.83,
      "NumberOfRatings": 6293
    },
    {
      "Time": "2022-08-27T03:32:18.029074+00:00",
      "Rating": 4.83,
      "NumberOfRatings": 6297
    },
    {
      "Time": "2022-08-27T05:02:18.9180111+00:00",
      "Rating": 4.83,
      "NumberOfRatings": 6298
    },
    {
      "Time": "2022-08-27T05:32:33.8899008+00:00",
      "Rating": 4.83,
      "NumberOfRatings": 6299
    },
    {
      "Time": "2022-08-27T06:32:15.1345168+00:00",
      "Rating": 4.83,
      "NumberOfRatings": 6301
    },
    {
      "Time": "2022-08-27T09:02:06.3423541+00:00",
      "Rating": 4.83,
      "NumberOfRatings": 6304
    },
    {
      "Time": "2022-08-27T12:01:57.3092537+00:00",
      "Rating": 4.83,
      "NumberOfRatings": 6317
    },
    {
      "Time": "2022-08-27T16:31:52.7653591+00:00",
      "Rating": 4.83,
      "NumberOfRatings": 6333
    },
    {
      "Time": "2022-08-27T18:31:54.1769845+00:00",
      "Rating": 4.83,
      "NumberOfRatings": 6338
    },
    {
      "Time": "2022-08-27T22:01:50.3770243+00:00",
      "Rating": 4.83,
      "NumberOfRatings": 6344
    },
    {
      "Time": "2022-08-27T23:31:50.2033314+00:00",
      "Rating": 4.83,
      "NumberOfRatings": 6346
    },
    {
      "Time": "2022-08-28T04:01:52.1101909+00:00",
      "Rating": 4.83,
      "NumberOfRatings": 6352
    },
    {
      "Time": "2022-08-28T06:31:52.9577987+00:00",
      "Rating": 4.83,
      "NumberOfRatings": 6356
    },
    {
      "Time": "2022-08-28T10:02:19.7412192+00:00",
      "Rating": 4.83,
      "NumberOfRatings": 6362
    },
    {
      "Time": "2022-08-28T11:01:58.0861186+00:00",
      "Rating": 4.83,
      "NumberOfRatings": 6367
    },
    {
      "Time": "2022-08-28T14:02:55.5751368+00:00",
      "Rating": 4.83,
      "NumberOfRatings": 6376
    },
    {
      "Time": "2022-08-28T17:02:03.0504245+00:00",
      "Rating": 4.83,
      "NumberOfRatings": 6380
    },
    {
      "Time": "2022-08-28T20:01:56.3338565+00:00",
      "Rating": 4.83,
      "NumberOfRatings": 6393
    },
    {
      "Time": "2022-08-29T00:01:59.0706939+00:00",
      "Rating": 4.83,
      "NumberOfRatings": 6404
    },
    {
      "Time": "2022-08-29T01:01:59.3120871+00:00",
      "Rating": 4.83,
      "NumberOfRatings": 6405
    },
    {
      "Time": "2022-08-29T05:01:49.7279422+00:00",
      "Rating": 4.83,
      "NumberOfRatings": 6412
    },
    {
      "Time": "2022-08-29T11:31:57.3395345+00:00",
      "Rating": 4.83,
      "NumberOfRatings": 6422
    },
    {
      "Time": "2022-08-29T14:03:12.7594378+00:00",
      "Rating": 4.83,
      "NumberOfRatings": 6425
    },
    {
      "Time": "2022-08-29T14:31:58.0641019+00:00",
      "Rating": 4.83,
      "NumberOfRatings": 6427
    },
    {
      "Time": "2022-08-29T16:02:22.222502+00:00",
      "Rating": 4.83,
      "NumberOfRatings": 6429
    },
    {
      "Time": "2022-08-29T17:02:28.5614606+00:00",
      "Rating": 4.83,
      "NumberOfRatings": 6434
    },
    {
      "Time": "2022-08-29T19:31:56.3485483+00:00",
      "Rating": 4.83,
      "NumberOfRatings": 6439
    },
    {
      "Time": "2022-08-29T20:01:56.7248062+00:00",
      "Rating": 4.83,
      "NumberOfRatings": 6443
    },
    {
      "Time": "2022-08-29T22:01:59.1479966+00:00",
      "Rating": 4.83,
      "NumberOfRatings": 6445
    },
    {
      "Time": "2022-08-30T03:31:53.7273863+00:00",
      "Rating": 4.83,
      "NumberOfRatings": 6454
    },
    {
      "Time": "2022-08-30T05:01:55.3659788+00:00",
      "Rating": 4.83,
      "NumberOfRatings": 6455
    },
    {
      "Time": "2022-08-30T08:02:06.3979773+00:00",
      "Rating": 4.83,
      "NumberOfRatings": 6460
    },
    {
      "Time": "2022-08-30T14:03:17.5358677+00:00",
      "Rating": 4.83,
      "NumberOfRatings": 6474
    },
    {
      "Time": "2022-08-30T16:02:46.4074508+00:00",
      "Rating": 4.83,
      "NumberOfRatings": 6478
    },
    {
      "Time": "2022-08-30T19:02:17.1833383+00:00",
      "Rating": 4.83,
      "NumberOfRatings": 6493
    },
    {
      "Time": "2022-08-30T21:02:21.0877685+00:00",
      "Rating": 4.83,
      "NumberOfRatings": 6499
    },
    {
      "Time": "2022-08-30T22:04:00.9383311+00:00",
      "Rating": 4.83,
      "NumberOfRatings": 6502
    },
    {
      "Time": "2022-08-31T00:32:22.6470437+00:00",
      "Rating": 4.83,
      "NumberOfRatings": 6507
    },
    {
      "Time": "2022-08-31T01:02:30.1117607+00:00",
      "Rating": 4.83,
      "NumberOfRatings": 6502
    },
    {
      "Time": "2022-08-31T03:32:16.1473957+00:00",
      "Rating": 4.83,
      "NumberOfRatings": 6513
    },
    {
      "Time": "2022-08-31T06:32:30.1948802+00:00",
      "Rating": 4.83,
      "NumberOfRatings": 6516
    },
    {
      "Time": "2022-08-31T07:32:11.9047695+00:00",
      "Rating": 4.83,
      "NumberOfRatings": 6519
    },
    {
      "Time": "2022-08-31T12:31:52.6990934+00:00",
      "Rating": 4.83,
      "NumberOfRatings": 6530
    },
    {
      "Time": "2022-08-31T14:32:01.6941933+00:00",
      "Rating": 4.83,
      "NumberOfRatings": 6542
    },
    {
      "Time": "2022-08-31T17:02:12.1854203+00:00",
      "Rating": 4.83,
      "NumberOfRatings": 6547
    },
    {
      "Time": "2022-08-31T17:32:07.5130567+00:00",
      "Rating": 4.83,
      "NumberOfRatings": 6549
    },
    {
      "Time": "2022-08-31T20:02:25.0219062+00:00",
      "Rating": 4.83,
      "NumberOfRatings": 6559
    },
    {
      "Time": "2022-09-01T00:31:51.6247286+00:00",
      "Rating": 4.83,
      "NumberOfRatings": 6574
    },
    {
      "Time": "2022-09-01T02:31:49.547121+00:00",
      "Rating": 4.83,
      "NumberOfRatings": 6577
    },
    {
      "Time": "2022-09-01T04:32:27.5215902+00:00",
      "Rating": 4.83,
      "NumberOfRatings": 6581
    },
    {
      "Time": "2022-09-01T06:31:51.4839562+00:00",
      "Rating": 4.83,
      "NumberOfRatings": 6583
    },
    {
      "Time": "2022-09-01T08:31:52.3369666+00:00",
      "Rating": 4.83,
      "NumberOfRatings": 6584
    },
    {
      "Time": "2022-09-01T09:32:16.755312+00:00",
      "Rating": 4.83,
      "NumberOfRatings": 6586
    },
    {
      "Time": "2022-09-01T12:02:33.6832755+00:00",
      "Rating": 4.83,
      "NumberOfRatings": 6592
    },
    {
      "Time": "2022-09-01T17:32:38.6002106+00:00",
      "Rating": 4.83,
      "NumberOfRatings": 6618
    },
    {
      "Time": "2022-09-01T18:31:56.5924759+00:00",
      "Rating": 4.83,
      "NumberOfRatings": 6623
    },
    {
      "Time": "2022-09-01T19:02:37.810097+00:00",
      "Rating": 4.83,
      "NumberOfRatings": 6629
    },
    {
      "Time": "2022-09-01T20:02:23.188472+00:00",
      "Rating": 4.83,
      "NumberOfRatings": 6633
    },
    {
      "Time": "2022-09-01T22:32:15.5854083+00:00",
      "Rating": 4.83,
      "NumberOfRatings": 6651
    },
    {
      "Time": "2022-09-02T00:31:55.9835789+00:00",
      "Rating": 4.83,
      "NumberOfRatings": 6657
    },
    {
      "Time": "2022-09-02T06:02:34.6198273+00:00",
      "Rating": 4.83,
      "NumberOfRatings": 6665
    },
    {
      "Time": "2022-09-02T12:02:00.5929687+00:00",
      "Rating": 4.83,
      "NumberOfRatings": 6675
    },
    {
      "Time": "2022-09-02T12:32:01.0972938+00:00",
      "Rating": 4.83,
      "NumberOfRatings": 6679
    },
    {
      "Time": "2022-09-02T15:02:04.3042091+00:00",
      "Rating": 4.83,
      "NumberOfRatings": 6683
    },
    {
      "Time": "2022-09-02T17:02:33.598591+00:00",
      "Rating": 4.83,
      "NumberOfRatings": 6687
    },
    {
      "Time": "2022-09-02T18:32:08.988902+00:00",
      "Rating": 4.83,
      "NumberOfRatings": 6690
    },
    {
      "Time": "2022-09-02T21:02:36.2241341+00:00",
      "Rating": 4.83,
      "NumberOfRatings": 6699
    },
    {
      "Time": "2022-09-02T22:31:57.5120423+00:00",
      "Rating": 4.83,
      "NumberOfRatings": 6702
    },
    {
      "Time": "2022-09-02T23:32:12.8164476+00:00",
      "Rating": 4.83,
      "NumberOfRatings": 6703
    },
    {
      "Time": "2022-09-03T00:02:46.672748+00:00",
      "Rating": 4.83,
      "NumberOfRatings": 6705
    },
    {
      "Time": "2022-09-03T01:32:13.7272136+00:00",
      "Rating": 4.83,
      "NumberOfRatings": 6709
    },
    {
      "Time": "2022-09-03T08:31:59.3307479+00:00",
      "Rating": 4.83,
      "NumberOfRatings": 6718
    },
    {
      "Time": "2022-09-03T12:02:21.3030448+00:00",
      "Rating": 4.83,
      "NumberOfRatings": 6723
    },
    {
      "Time": "2022-09-03T13:32:01.4852196+00:00",
      "Rating": 4.83,
      "NumberOfRatings": 6725
    },
    {
      "Time": "2022-09-03T14:32:12.5090753+00:00",
      "Rating": 4.83,
      "NumberOfRatings": 6727
    },
    {
      "Time": "2022-09-03T17:32:12.1532662+00:00",
      "Rating": 4.83,
      "NumberOfRatings": 6737
    },
    {
      "Time": "2022-09-03T19:02:26.866836+00:00",
      "Rating": 4.83,
      "NumberOfRatings": 6744
    },
    {
      "Time": "2022-09-03T21:02:25.6851585+00:00",
      "Rating": 4.83,
      "NumberOfRatings": 6750
    },
    {
      "Time": "2022-09-03T22:02:23.6365218+00:00",
      "Rating": 4.83,
      "NumberOfRatings": 6754
    },
    {
      "Time": "2022-09-03T23:32:23.7409669+00:00",
      "Rating": 4.83,
      "NumberOfRatings": 6758
    },
    {
      "Time": "2022-09-04T01:02:20.2591021+00:00",
      "Rating": 4.83,
      "NumberOfRatings": 6762
    },
    {
      "Time": "2022-09-04T09:01:58.7434486+00:00",
      "Rating": 4.83,
      "NumberOfRatings": 6775
    },
    {
      "Time": "2022-09-04T09:33:10.2226628+00:00",
      "Rating": 4.83,
      "NumberOfRatings": 6777
    },
    {
      "Time": "2022-09-04T13:32:01.4575383+00:00",
      "Rating": 4.83,
      "NumberOfRatings": 6792
    },
    {
      "Time": "2022-09-04T15:02:05.3490942+00:00",
      "Rating": 4.83,
      "NumberOfRatings": 6794
    },
    {
      "Time": "2022-09-04T19:02:30.5140242+00:00",
      "Rating": 4.83,
      "NumberOfRatings": 6826
    },
    {
      "Time": "2022-09-04T21:31:52.8861977+00:00",
      "Rating": 4.83,
      "NumberOfRatings": 6836
    },
    {
      "Time": "2022-09-04T22:01:51.5244151+00:00",
      "Rating": 4.83,
      "NumberOfRatings": 6841
    },
    {
      "Time": "2022-09-05T01:02:00.5649953+00:00",
      "Rating": 4.83,
      "NumberOfRatings": 6843
    },
    {
      "Time": "2022-09-05T04:02:14.8418569+00:00",
      "Rating": 4.83,
      "NumberOfRatings": 6848
    },
    {
      "Time": "2022-09-05T06:01:51.865269+00:00",
      "Rating": 4.83,
      "NumberOfRatings": 6849
    },
    {
      "Time": "2022-09-05T08:31:50.4920376+00:00",
      "Rating": 4.83,
      "NumberOfRatings": 6853
    },
    {
      "Time": "2022-09-05T10:32:17.7661959+00:00",
      "Rating": 4.83,
      "NumberOfRatings": 6854
    },
    {
      "Time": "2022-09-05T15:01:53.1944836+00:00",
      "Rating": 4.83,
      "NumberOfRatings": 6860
    },
    {
      "Time": "2022-09-05T18:01:52.4102945+00:00",
      "Rating": 4.83,
      "NumberOfRatings": 6868
    },
    {
      "Time": "2022-09-05T22:01:53.3847605+00:00",
      "Rating": 4.83,
      "NumberOfRatings": 6882
    },
    {
      "Time": "2022-09-06T03:01:54.680492+00:00",
      "Rating": 4.83,
      "NumberOfRatings": 6888
    },
    {
      "Time": "2022-09-06T05:02:55.5597687+00:00",
      "Rating": 4.83,
      "NumberOfRatings": 6892
    },
    {
      "Time": "2022-09-06T08:31:53.5531814+00:00",
      "Rating": 4.83,
      "NumberOfRatings": 6898
    },
    {
      "Time": "2022-09-06T12:01:54.0241217+00:00",
      "Rating": 4.83,
      "NumberOfRatings": 6901
    },
    {
      "Time": "2022-09-06T12:31:55.9577146+00:00",
      "Rating": 4.83,
      "NumberOfRatings": 6903
    },
    {
      "Time": "2022-09-06T13:31:52.0016082+00:00",
      "Rating": 4.83,
      "NumberOfRatings": 6908
    },
    {
      "Time": "2022-09-06T17:02:06.8072157+00:00",
      "Rating": 4.83,
      "NumberOfRatings": 6920
    },
    {
      "Time": "2022-09-06T23:01:55.817361+00:00",
      "Rating": 4.83,
      "NumberOfRatings": 6940
    },
    {
      "Time": "2022-09-07T01:32:26.3376792+00:00",
      "Rating": 4.83,
      "NumberOfRatings": 6944
    },
    {
      "Time": "2022-09-07T02:01:52.4993366+00:00",
      "Rating": 4.83,
      "NumberOfRatings": 6945
    },
    {
      "Time": "2022-09-07T08:02:07.0894448+00:00",
      "Rating": 4.83,
      "NumberOfRatings": 6954
    },
    {
      "Time": "2022-09-07T08:31:56.6160229+00:00",
      "Rating": 4.83,
      "NumberOfRatings": 6956
    },
    {
      "Time": "2022-09-07T10:02:05.6517938+00:00",
      "Rating": 4.83,
      "NumberOfRatings": 6959
    },
    {
      "Time": "2022-09-07T14:32:13.7611995+00:00",
      "Rating": 4.83,
      "NumberOfRatings": 6968
    },
    {
      "Time": "2022-09-07T15:32:55.1306037+00:00",
      "Rating": 4.83,
      "NumberOfRatings": 6973
    },
    {
      "Time": "2022-09-07T16:32:13.7266422+00:00",
      "Rating": 4.83,
      "NumberOfRatings": 6978
    },
    {
      "Time": "2022-09-07T19:33:01.8711771+00:00",
      "Rating": 4.83,
      "NumberOfRatings": 6986
    },
    {
      "Time": "2022-09-07T22:02:43.8684998+00:00",
      "Rating": 4.83,
      "NumberOfRatings": 6998
    },
    {
      "Time": "2022-09-07T23:02:16.8181273+00:00",
      "Rating": 4.83,
      "NumberOfRatings": 7001
    },
    {
      "Time": "2022-09-08T09:01:55.1068294+00:00",
      "Rating": 4.83,
      "NumberOfRatings": 7017
    },
    {
      "Time": "2022-09-08T10:02:09.4678372+00:00",
      "Rating": 4.83,
      "NumberOfRatings": 7021
    },
    {
      "Time": "2022-09-08T12:02:35.3753003+00:00",
      "Rating": 4.83,
      "NumberOfRatings": 7023
    },
    {
      "Time": "2022-09-08T16:31:51.8790134+00:00",
      "Rating": 4.83,
      "NumberOfRatings": 7035
    },
    {
      "Time": "2022-09-08T18:31:53.2479715+00:00",
      "Rating": 4.83,
      "NumberOfRatings": 7047
    },
    {
      "Time": "2022-09-08T22:02:27.8763368+00:00",
      "Rating": 4.83,
      "NumberOfRatings": 7049
    },
    {
      "Time": "2022-09-08T23:01:58.2640092+00:00",
      "Rating": 4.83,
      "NumberOfRatings": 7052
    },
    {
      "Time": "2022-09-09T02:31:51.5556809+00:00",
      "Rating": 4.83,
      "NumberOfRatings": 7060
    },
    {
      "Time": "2022-09-09T03:02:29.0669275+00:00",
      "Rating": 4.83,
      "NumberOfRatings": 7062
    },
    {
      "Time": "2022-09-09T11:01:56.7586479+00:00",
      "Rating": 4.83,
      "NumberOfRatings": 7073
    },
    {
      "Time": "2022-09-09T13:02:32.4226868+00:00",
      "Rating": 4.83,
      "NumberOfRatings": 7080
    },
    {
      "Time": "2022-09-09T13:31:56.0012071+00:00",
      "Rating": 4.83,
      "NumberOfRatings": 7082
    },
    {
      "Time": "2022-09-09T18:02:03.4147243+00:00",
      "Rating": 4.83,
      "NumberOfRatings": 7109
    },
    {
      "Time": "2022-09-09T19:03:08.5979041+00:00",
      "Rating": 4.83,
      "NumberOfRatings": 7114
    },
    {
      "Time": "2022-09-09T20:32:26.7723498+00:00",
      "Rating": 4.83,
      "NumberOfRatings": 7126
    },
    {
      "Time": "2022-09-09T23:02:01.1484713+00:00",
      "Rating": 4.83,
      "NumberOfRatings": 7130
    },
    {
      "Time": "2022-09-10T01:32:18.3980803+00:00",
      "Rating": 4.83,
      "NumberOfRatings": 7136
    },
    {
      "Time": "2022-09-10T09:31:55.6151534+00:00",
      "Rating": 4.83,
      "NumberOfRatings": 7153
    },
    {
      "Time": "2022-09-10T12:01:56.0246755+00:00",
      "Rating": 4.83,
      "NumberOfRatings": 7165
    },
    {
      "Time": "2022-09-10T13:32:01.5883246+00:00",
      "Rating": 4.83,
      "NumberOfRatings": 7170
    },
    {
      "Time": "2022-09-10T15:01:57.0202567+00:00",
      "Rating": 4.83,
      "NumberOfRatings": 7180
    },
    {
      "Time": "2022-09-10T17:31:54.5492385+00:00",
      "Rating": 4.83,
      "NumberOfRatings": 7186
    },
    {
      "Time": "2022-09-10T18:31:56.2800567+00:00",
      "Rating": 4.83,
      "NumberOfRatings": 7190
    },
    {
      "Time": "2022-09-10T20:03:26.0811716+00:00",
      "Rating": 4.83,
      "NumberOfRatings": 7196
    },
    {
      "Time": "2022-09-10T22:31:53.749152+00:00",
      "Rating": 4.83,
      "NumberOfRatings": 7204
    },
    {
      "Time": "2022-09-11T00:31:56.1675814+00:00",
      "Rating": 4.83,
      "NumberOfRatings": 7206
    },
    {
      "Time": "2022-09-11T04:32:44.6127277+00:00",
      "Rating": 4.83,
      "NumberOfRatings": 7213
    },
    {
      "Time": "2022-09-11T08:02:11.9522321+00:00",
      "Rating": 4.83,
      "NumberOfRatings": 7222
    },
    {
      "Time": "2022-09-11T13:32:11.6144988+00:00",
      "Rating": 4.83,
      "NumberOfRatings": 7245
    },
    {
      "Time": "2022-09-11T19:02:23.1285671+00:00",
      "Rating": 4.83,
      "NumberOfRatings": 7258
    },
    {
      "Time": "2022-09-11T22:32:46.7626477+00:00",
      "Rating": 4.83,
      "NumberOfRatings": 7269
    },
    {
      "Time": "2022-09-12T03:32:24.8039181+00:00",
      "Rating": 4.83,
      "NumberOfRatings": 7276
    },
    {
      "Time": "2022-09-12T05:02:37.2299583+00:00",
      "Rating": 4.83,
      "NumberOfRatings": 7277
    },
    {
      "Time": "2022-09-12T06:02:10.1588282+00:00",
      "Rating": 4.83,
      "NumberOfRatings": 7279
    },
    {
      "Time": "2022-09-12T13:31:54.4477907+00:00",
      "Rating": 4.83,
      "NumberOfRatings": 7284
    },
    {
      "Time": "2022-09-12T14:31:57.1173469+00:00",
      "Rating": 4.83,
      "NumberOfRatings": 7289
    },
    {
      "Time": "2022-09-12T16:31:57.5790596+00:00",
      "Rating": 4.83,
      "NumberOfRatings": 7296
    },
    {
      "Time": "2022-09-12T17:33:06.4149187+00:00",
      "Rating": 4.83,
      "NumberOfRatings": 7300
    },
    {
      "Time": "2022-09-12T19:02:11.3572673+00:00",
      "Rating": 4.83,
      "NumberOfRatings": 7303
    },
    {
      "Time": "2022-09-12T20:02:06.9865678+00:00",
      "Rating": 4.83,
      "NumberOfRatings": 7305
    },
    {
      "Time": "2022-09-12T21:31:55.3629342+00:00",
      "Rating": 4.83,
      "NumberOfRatings": 7315
    },
    {
      "Time": "2022-09-13T02:02:12.3011989+00:00",
      "Rating": 4.83,
      "NumberOfRatings": 7325
    },
    {
      "Time": "2022-09-13T14:31:54.3357465+00:00",
      "Rating": 4.83,
      "NumberOfRatings": 7345
    },
    {
      "Time": "2022-09-13T15:32:04.5638397+00:00",
      "Rating": 4.83,
      "NumberOfRatings": 7348
    },
    {
      "Time": "2022-09-13T18:02:51.4674394+00:00",
      "Rating": 4.83,
      "NumberOfRatings": 7354
    },
    {
      "Time": "2022-09-13T20:01:58.4995932+00:00",
      "Rating": 4.83,
      "NumberOfRatings": 7365
    },
    {
      "Time": "2022-09-13T22:32:35.042778+00:00",
      "Rating": 4.83,
      "NumberOfRatings": 7372
    },
    {
      "Time": "2022-09-14T01:01:57.2893451+00:00",
      "Rating": 4.83,
      "NumberOfRatings": 7378
    },
    {
      "Time": "2022-09-14T12:02:27.8251904+00:00",
      "Rating": 4.83,
      "NumberOfRatings": 7387
    },
    {
      "Time": "2022-09-14T14:02:24.5726252+00:00",
      "Rating": 4.83,
      "NumberOfRatings": 7392
    },
    {
      "Time": "2022-09-14T15:02:34.2924856+00:00",
      "Rating": 4.83,
      "NumberOfRatings": 7396
    },
    {
      "Time": "2022-09-14T15:31:54.2804119+00:00",
      "Rating": 4.83,
      "NumberOfRatings": 7398
    },
    {
      "Time": "2022-09-14T19:02:58.6949891+00:00",
      "Rating": 4.83,
      "NumberOfRatings": 7413
    },
    {
      "Time": "2022-09-14T20:02:16.8905987+00:00",
      "Rating": 4.83,
      "NumberOfRatings": 7415
    },
    {
      "Time": "2022-09-14T21:02:40.4729363+00:00",
      "Rating": 4.83,
      "NumberOfRatings": 7418
    },
    {
      "Time": "2022-09-15T03:01:59.4947516+00:00",
      "Rating": 4.83,
      "NumberOfRatings": 7432
    },
    {
      "Time": "2022-09-15T07:04:10.82234+00:00",
      "Rating": 4.83,
      "NumberOfRatings": 7438
    },
    {
      "Time": "2022-09-15T09:02:11.0917601+00:00",
      "Rating": 4.83,
      "NumberOfRatings": 7442
    },
    {
      "Time": "2022-09-15T11:02:29.7747995+00:00",
      "Rating": 4.83,
      "NumberOfRatings": 7445
    },
    {
      "Time": "2022-09-15T13:02:27.5959527+00:00",
      "Rating": 4.83,
      "NumberOfRatings": 7451
    },
    {
      "Time": "2022-09-15T16:02:57.1671602+00:00",
      "Rating": 4.83,
      "NumberOfRatings": 7464
    },
    {
      "Time": "2022-09-15T17:02:43.1036227+00:00",
      "Rating": 4.83,
      "NumberOfRatings": 7476
    },
    {
      "Time": "2022-09-15T18:32:24.7760649+00:00",
      "Rating": 4.83,
      "NumberOfRatings": 7483
    },
    {
      "Time": "2022-09-16T03:02:50.3327283+00:00",
      "Rating": 4.83,
      "NumberOfRatings": 7503
    },
    {
      "Time": "2022-09-16T03:32:01.4847895+00:00",
      "Rating": 4.83,
      "NumberOfRatings": 7507
    },
    {
      "Time": "2022-09-16T04:32:01.8510169+00:00",
      "Rating": 4.83,
      "NumberOfRatings": 7508
    },
    {
      "Time": "2022-09-16T07:32:28.1387648+00:00",
      "Rating": 4.83,
      "NumberOfRatings": 7509
    },
    {
      "Time": "2022-09-16T08:03:06.2721823+00:00",
      "Rating": 4.83,
      "NumberOfRatings": 7512
    },
    {
      "Time": "2022-09-16T13:02:42.7740275+00:00",
      "Rating": 4.83,
      "NumberOfRatings": 7522
    },
    {
      "Time": "2022-09-16T13:31:59.6261164+00:00",
      "Rating": 4.83,
      "NumberOfRatings": 7526
    },
    {
      "Time": "2022-09-16T14:31:56.1358482+00:00",
      "Rating": 4.83,
      "NumberOfRatings": 7530
    },
    {
      "Time": "2022-09-16T16:31:53.8130461+00:00",
      "Rating": 4.83,
      "NumberOfRatings": 7532
    },
    {
      "Time": "2022-09-16T18:31:59.1660344+00:00",
      "Rating": 4.83,
      "NumberOfRatings": 7543
    },
    {
      "Time": "2022-09-16T19:02:05.1462537+00:00",
      "Rating": 4.83,
      "NumberOfRatings": 7548
    },
    {
      "Time": "2022-09-16T20:31:55.1890804+00:00",
      "Rating": 4.83,
      "NumberOfRatings": 7549
    },
    {
      "Time": "2022-09-16T23:32:36.2686673+00:00",
      "Rating": 4.83,
      "NumberOfRatings": 7560
    },
    {
      "Time": "2022-09-17T09:02:49.5534486+00:00",
      "Rating": 4.83,
      "NumberOfRatings": 7587
    },
    {
      "Time": "2022-09-17T11:01:59.2552066+00:00",
      "Rating": 4.83,
      "NumberOfRatings": 7595
    },
    {
      "Time": "2022-09-17T13:01:55.8506843+00:00",
      "Rating": 4.83,
      "NumberOfRatings": 7602
    },
    {
      "Time": "2022-09-17T14:32:26.4784681+00:00",
      "Rating": 4.83,
      "NumberOfRatings": 7606
    },
    {
      "Time": "2022-09-17T16:01:54.8760331+00:00",
      "Rating": 4.83,
      "NumberOfRatings": 7608
    },
    {
      "Time": "2022-09-17T16:31:59.8250331+00:00",
      "Rating": 4.83,
      "NumberOfRatings": 7610
    },
    {
      "Time": "2022-09-17T20:03:04.5383632+00:00",
      "Rating": 4.83,
      "NumberOfRatings": 7620
    },
    {
      "Time": "2022-09-17T21:01:58.0712698+00:00",
      "Rating": 4.83,
      "NumberOfRatings": 7624
    },
    {
      "Time": "2022-09-18T03:31:53.7602898+00:00",
      "Rating": 4.83,
      "NumberOfRatings": 7638
    },
    {
      "Time": "2022-09-18T10:32:03.0905058+00:00",
      "Rating": 4.83,
      "NumberOfRatings": 7650
    },
    {
      "Time": "2022-09-18T13:02:16.9212608+00:00",
      "Rating": 4.83,
      "NumberOfRatings": 7658
    },
    {
      "Time": "2022-09-18T13:32:00.000559+00:00",
      "Rating": 4.83,
      "NumberOfRatings": 7664
    },
    {
      "Time": "2022-09-18T14:02:30.8918309+00:00",
      "Rating": 4.83,
      "NumberOfRatings": 7665
    },
    {
      "Time": "2022-09-18T16:31:58.362783+00:00",
      "Rating": 4.83,
      "NumberOfRatings": 7677
    },
    {
      "Time": "2022-09-18T18:32:00.0942079+00:00",
      "Rating": 4.83,
      "NumberOfRatings": 7685
    },
    {
      "Time": "2022-09-18T20:32:02.5327622+00:00",
      "Rating": 4.83,
      "NumberOfRatings": 7693
    },
    {
      "Time": "2022-09-18T21:31:55.5654666+00:00",
      "Rating": 4.83,
      "NumberOfRatings": 7696
    },
    {
      "Time": "2022-09-19T03:02:20.3874961+00:00",
      "Rating": 4.83,
      "NumberOfRatings": 7710
    },
    {
      "Time": "2022-09-19T12:32:08.4717231+00:00",
      "Rating": 4.83,
      "NumberOfRatings": 7725
    },
    {
      "Time": "2022-09-19T14:02:39.0476887+00:00",
      "Rating": 4.83,
      "NumberOfRatings": 7730
    },
    {
      "Time": "2022-09-19T16:03:09.9934842+00:00",
      "Rating": 4.83,
      "NumberOfRatings": 7734
    },
    {
      "Time": "2022-09-19T16:32:36.5997293+00:00",
      "Rating": 4.83,
      "NumberOfRatings": 7737
    },
    {
      "Time": "2022-09-19T17:33:05.8818704+00:00",
      "Rating": 4.83,
      "NumberOfRatings": 7742
    },
    {
      "Time": "2022-09-19T18:32:40.7529804+00:00",
      "Rating": 4.83,
      "NumberOfRatings": 7744
    },
    {
      "Time": "2022-09-19T21:04:45.4282688+00:00",
      "Rating": 4.83,
      "NumberOfRatings": 7749
    },
    {
      "Time": "2022-09-19T22:02:31.2358334+00:00",
      "Rating": 4.83,
      "NumberOfRatings": 7752
    },
    {
      "Time": "2022-09-20T00:03:34.326854+00:00",
      "Rating": 4.83,
      "NumberOfRatings": 7754
    },
    {
      "Time": "2022-09-20T03:32:45.3013835+00:00",
      "Rating": 4.83,
      "NumberOfRatings": 7762
    },
    {
      "Time": "2022-09-20T05:32:49.0806359+00:00",
      "Rating": 4.83,
      "NumberOfRatings": 7763
    },
    {
      "Time": "2022-09-20T09:32:22.3677488+00:00",
      "Rating": 4.83,
      "NumberOfRatings": 7766
    },
    {
      "Time": "2022-09-20T16:32:07.7036612+00:00",
      "Rating": 4.83,
      "NumberOfRatings": 7789
    },
    {
      "Time": "2022-09-20T18:03:00.5656982+00:00",
      "Rating": 4.83,
      "NumberOfRatings": 7791
    },
    {
      "Time": "2022-09-20T18:32:04.5931597+00:00",
      "Rating": 4.83,
      "NumberOfRatings": 7795
    },
    {
      "Time": "2022-09-20T19:32:05.4001905+00:00",
      "Rating": 4.83,
      "NumberOfRatings": 7797
    },
    {
      "Time": "2022-09-20T20:02:40.0196951+00:00",
      "Rating": 4.83,
      "NumberOfRatings": 7800
    },
    {
      "Time": "2022-09-20T22:02:03.129437+00:00",
      "Rating": 4.83,
      "NumberOfRatings": 7804
    },
    {
      "Time": "2022-09-21T15:02:11.2548695+00:00",
      "Rating": 4.83,
      "NumberOfRatings": 7828
    },
    {
      "Time": "2022-09-21T18:02:58.204255+00:00",
      "Rating": 4.83,
      "NumberOfRatings": 7838
    },
    {
      "Time": "2022-09-21T19:02:07.6374982+00:00",
      "Rating": 4.83,
      "NumberOfRatings": 7841
    },
    {
      "Time": "2022-09-21T21:32:38.4521268+00:00",
      "Rating": 4.83,
      "NumberOfRatings": 7846
    },
    {
      "Time": "2022-09-21T23:02:23.7190834+00:00",
      "Rating": 4.83,
      "NumberOfRatings": 7849
    },
    {
      "Time": "2022-09-22T00:32:02.4959977+00:00",
      "Rating": 4.83,
      "NumberOfRatings": 7850
    },
    {
      "Time": "2022-09-22T02:31:55.1378454+00:00",
      "Rating": 4.83,
      "NumberOfRatings": 7854
    },
    {
      "Time": "2022-09-22T06:31:56.5292275+00:00",
      "Rating": 4.83,
      "NumberOfRatings": 7857
    },
    {
      "Time": "2022-09-22T10:31:55.368416+00:00",
      "Rating": 4.83,
      "NumberOfRatings": 7862
    },
    {
      "Time": "2022-09-22T17:02:39.026531+00:00",
      "Rating": 4.83,
      "NumberOfRatings": 7872
    },
    {
      "Time": "2022-09-22T22:32:10.6657658+00:00",
      "Rating": 4.83,
      "NumberOfRatings": 7895
    },
    {
      "Time": "2022-09-23T01:32:41.8205351+00:00",
      "Rating": 4.83,
      "NumberOfRatings": 7904
    },
    {
      "Time": "2022-09-23T03:02:34.3997883+00:00",
      "Rating": 4.83,
      "NumberOfRatings": 7908
    },
    {
      "Time": "2022-09-23T05:32:00.455228+00:00",
      "Rating": 4.83,
      "NumberOfRatings": 7910
    },
    {
      "Time": "2022-09-23T06:31:56.1181782+00:00",
      "Rating": 4.83,
      "NumberOfRatings": 7912
    },
    {
      "Time": "2022-09-23T08:02:38.9970427+00:00",
      "Rating": 4.83,
      "NumberOfRatings": 7914
    },
    {
      "Time": "2022-09-23T09:32:12.2177909+00:00",
      "Rating": 4.83,
      "NumberOfRatings": 7920
    },
    {
      "Time": "2022-09-23T12:32:11.3992794+00:00",
      "Rating": 4.83,
      "NumberOfRatings": 7928
    },
    {
      "Time": "2022-10-06T16:32:56.8490319+00:00",
      "Rating": 4.84,
      "NumberOfRatings": null
    },
    {
      "Time": "2022-10-08T18:32:30.1046443+00:00",
      "Rating": 4.83,
      "NumberOfRatings": null
    },
    {
      "Time": "2022-10-09T06:32:02.0410108+00:00",
      "Rating": 4.84,
      "NumberOfRatings": null
    },
    {
      "Time": "2022-10-13T16:02:47.7783266+00:00",
      "Rating": 4.83,
      "NumberOfRatings": null
    },
    {
      "Time": "2022-10-14T17:02:15.6891176+00:00",
      "Rating": 4.84,
      "NumberOfRatings": null
    }
  ],
  "Tags": [
    {
      "Text": "This game has Amazing Storytelling",
      "Count": 597
    },
    {
      "Text": "This game is Highly Recommended",
      "Count": 560
    },
    {
      "Text": "This game is Great for Beginners",
      "Count": 572
    },
    {
      "Text": "This game has Obsessive Gameplay",
      "Count": 399
    },
    {
      "Text": "This game has Quickly Understood Controls",
      "Count": 556
    },
    {
      "Text": "This game is Extremely Fun",
      "Count": 536
    },
    {
      "Text": "This game is Relaxing",
      "Count": 566
    },
    {
      "Text": "This game has Amazing Characters",
      "Count": 470
    },
    {
      "Text": "This game is Educational",
      "Count": 482
    },
    {
      "Text": "This game has a Creative Community",
      "Count": 378
    },
    {
      "Text": "This game has Beautiful Visuals",
      "Count": 149
    }
  ]
}