{
  "ID": "5645a537b6a44f6f82d122729f3253ed",
  "Name": "Mutazione",
  "Names": [],
  "Rating": 4.69,
  "NumberOfRatings": 51,
  "DailyRatings": 1.17,
  "FirstSeen": "2022-07-22T20:26:44.0004019+00:00",
  "LastChanged": "2022-08-09T16:31:29.0614605+00:00",
  "RatingHistory": [
    {
      "Time": "2022-07-22T20:26:44.0004039+00:00",
      "Rating": 4.68,
      "NumberOfRatings": 34
    },
    {
      "Time": "2022-07-24T16:02:23.9969991+00:00",
      "Rating": 4.69,
      "NumberOfRatings": 35
    },
    {
      "Time": "2022-07-25T14:02:43.3547459+00:00",
      "Rating": 4.69,
      "NumberOfRatings": 36
    },
    {
      "Time": "2022-07-26T14:03:36.8696981+00:00",
      "Rating": 4.72,
      "NumberOfRatings": 39
    },
    {
      "Time": "2022-07-28T17:05:20.7665724+00:00",
      "Rating": 4.73,
      "NumberOfRatings": 41
    },
    {
      "Time": "2022-08-02T21:01:35.5914012+00:00",
      "Rating": 4.65,
      "NumberOfRatings": 43
    },
    {
      "Time": "2022-08-03T12:02:12.6937478+00:00",
      "Rating": 4.66,
      "NumberOfRatings": 44
    },
    {
      "Time": "2022-08-03T12:31:38.9054527+00:00",
      "Rating": 4.65,
      "NumberOfRatings": 43
    },
    {
      "Time": "2022-08-03T21:01:38.5361377+00:00",
      "Rating": 4.67,
      "NumberOfRatings": 45
    },
    {
      "Time": "2022-08-04T21:01:27.8096628+00:00",
      "Rating": 4.68,
      "NumberOfRatings": 47
    },
    {
      "Time": "2022-08-05T16:02:22.2620088+00:00",
      "Rating": 4.67,
      "NumberOfRatings": 49
    },
    {
      "Time": "2022-08-07T16:01:46.6923636+00:00",
      "Rating": 4.68,
      "NumberOfRatings": 50
    },
    {
      "Time": "2022-08-09T16:31:29.0614607+00:00",
      "Rating": 4.69,
      "NumberOfRatings": 51
    }
  ],
  "Tags": []
}